agentfabric/__init__.py
agentfabric/cli.py
agentfabric/fabric.py
agentfabric/artifacts/__init__.py
agentfabric/artifacts/store.py
agentfabric/config/__init__.py
agentfabric/config/loader.py
agentfabric/config/spec.py
agentfabric/db/__init__.py
agentfabric/db/facade.py
agentfabric/db/query.py
agentfabric/schema/__init__.py
agentfabric/schema/builder.py
agentfabric/schema/migrate.py
agentfabric/schema/orm.py
agentfabric/schema/registry.py
agentfabric/schema/types.py
agentfabric/ui/__init__.py
agentfabric/ui/_conn.py
agentfabric/ui/_delete_panel.py
agentfabric/ui/_filters.py
agentfabric/ui/_preview.py
agentfabric/ui/_relations.py
agentfabric/ui/_styles.py
agentfabric/ui/_ui_query.py
agentfabric/ui/app.py
agentfabric-0.2.1.dist-info/METADATA
agentfabric-0.2.1.dist-info/WHEEL
agentfabric-0.2.1.dist-info/entry_points.txt
agentfabric-0.2.1.dist-info/licenses/LICENSE
agentfabric-0.2.1.dist-info/RECORD
