Metadata-Version: 2.4
Name: agentfabric
Version: 0.2.1
Summary: Config-driven database component for agent pipelines (PostgreSQL + SQLAlchemy + Pydantic + fsspec).
Project-URL: Homepage, https://github.com/potatoQi/AgentFabric
Author: AgentFabric
License:                                  Apache License
License-File: LICENSE
Classifier: License :: OSI Approved :: Apache Software License
Requires-Python: >=3.10
Requires-Dist: fsspec>=2024.3.0
Requires-Dist: pandas>=2.0
Requires-Dist: psycopg[binary]>=3.1
Requires-Dist: pydantic>=2.6
Requires-Dist: pyyaml>=6.0
Requires-Dist: sqlalchemy>=2.0
Requires-Dist: streamlit>=1.33
